bq_jobrunner/__init__.py
bq_jobrunner/bq_jobrunner.py
bq_jobrunner-0.1.3.dist-info/LICENSE
bq_jobrunner-0.1.3.dist-info/METADATA
bq_jobrunner-0.1.3.dist-info/WHEEL
bq_jobrunner-0.1.3.dist-info/top_level.txt
bq_jobrunner-0.1.3.dist-info/RECORD
